hyperliquid/__init__.py
hyperliquid/api.py
hyperliquid/async_api.py
hyperliquid/async_exchange.py
hyperliquid/async_info.py
hyperliquid/exchange.py
hyperliquid/info.py
hyperliquid/trader.py
hyperliquid/utils/__init__.py
hyperliquid/utils/constants.py
hyperliquid/utils/error.py
hyperliquid/utils/signing.py
hyperliquid/utils/types.py
hyperliquid/websocket_manager.py
hyperliquid_python_sdk_xiangyu-0.15.1.dist-info/entry_points.txt
hyperliquid_python_sdk_xiangyu-0.15.1.dist-info/LICENSE.md
hyperliquid_python_sdk_xiangyu-0.15.1.dist-info/METADATA
hyperliquid_python_sdk_xiangyu-0.15.1.dist-info/WHEEL
hyperliquid_python_sdk_xiangyu-0.15.1.dist-info/RECORD
